[
  {
    "id": "1381094440022999043",
    "text": "#Bitcoin is a swarm of cyber hornets serving the goddess of wisdom, feeding on the fire of truth, exponentially growing ever smarter, faster, and stronger behind a wall of encrypted energy. - @michael_saylor \n\n#everydays https://t.co/NX2pcDqsT9",
    "authorId": "34097500",
    "authorUsername": "beeple",
    "publicMetrics": {
      "retweet_count": 1083,
      "reply_count": 437,
      "like_count": 8156,
      "quote_count": 188,
      "bookmark_count": 126,
      "impression_count": 0
    },
    "editHistoryTweetIds": [
      "1381094440022999043"
    ],
    "realCreatedAt": "2021-04-11T03:59:08.000Z",
    "attachments": {
      "media_keys": [
        "3_1381094184707325952"
      ]
    },
    "contextAnnotations": [
      {
        "domain": {
          "id": "45",
          "name": "Brand Vertical",
          "description": "Top level entities that describe a Brands industry"
        },
        "entity": {
          "id": "781974596148793345",
          "name": "Business & finance"
        }
      },
      {
        "domain": {
          "id": "30",
          "name": "Entities [Entity Service]",
          "description": "Entity Service top level domain, every item that is in Entity Service should be in this domain"
        },
        "entity": {
          "id": "781974596794716162",
          "name": "Financial services"
        }
      },
      {
        "domain": {
          "id": "30",
          "name": "Entities [Entity Service]",
          "description": "Entity Service top level domain, every item that is in Entity Service should be in this domain"
        },
        "entity": {
          "id": "1007360414114435072",
          "name": "Bitcoin cryptocurrency",
          "description": "Bitcoin Cryptocurrency"
        }
      },
      {
        "domain": {
          "id": "65",
          "name": "Interests and Hobbies Vertical",
          "description": "Top level interests and hobbies groupings, like Food or Travel"
        },
        "entity": {
          "id": "781974596148793345",
          "name": "Business & finance"
        }
      },
      {
        "domain": {
          "id": "66",
          "name": "Interests and Hobbies Category",
          "description": "A grouping of interests and hobbies entities, like Novelty Food or Destinations"
        },
        "entity": {
          "id": "847888632711061504",
          "name": "Personal finance",
          "description": "Personal finance"
        }
      },
      {
        "domain": {
          "id": "66",
          "name": "Interests and Hobbies Category",
          "description": "A grouping of interests and hobbies entities, like Novelty Food or Destinations"
        },
        "entity": {
          "id": "913142676819648512",
          "name": "Cryptocurrencies",
          "description": "Cryptocurrency"
        }
      },
      {
        "domain": {
          "id": "131",
          "name": "Unified Twitter Taxonomy",
          "description": "A taxonomy of user interests. "
        },
        "entity": {
          "id": "781974596148793345",
          "name": "Business & finance"
        }
      },
      {
        "domain": {
          "id": "131",
          "name": "Unified Twitter Taxonomy",
          "description": "A taxonomy of user interests. "
        },
        "entity": {
          "id": "913142676819648512",
          "name": "Cryptocurrencies",
          "description": "Cryptocurrency"
        }
      },
      {
        "domain": {
          "id": "131",
          "name": "Unified Twitter Taxonomy",
          "description": "A taxonomy of user interests. "
        },
        "entity": {
          "id": "1007360414114435072",
          "name": "Bitcoin cryptocurrency",
          "description": "Bitcoin Cryptocurrency"
        }
      }
    ],
    "lang": "en",
    "keyword": "bitcoin"
  },
  {
    "id": "1333636005694418944",
    "text": "ALL TIME HIGH #Bitcoin https://t.co/h8JndYEC1w",
    "authorId": "34097500",
    "authorUsername": "beeple",
    "publicMetrics": {
      "retweet_count": 122,
      "reply_count": 29,
      "like_count": 1858,
      "quote_count": 22,
      "bookmark_count": 11,
      "impression_count": 0
    },
    "editHistoryTweetIds": [
      "1333636005694418944"
    ],
    "realCreatedAt": "2020-12-01T04:56:16.000Z",
    "attachments": {
      "media_keys": [
        "3_1333635047723835393"
      ]
    },
    "contextAnnotations": [
      {
        "domain": {
          "id": "45",
          "name": "Brand Vertical",
          "description": "Top level entities that describe a Brands industry"
        },
        "entity": {
          "id": "781974596148793345",
          "name": "Business & finance"
        }
      },
      {
        "domain": {
          "id": "30",
          "name": "Entities [Entity Service]",
          "description": "Entity Service top level domain, every item that is in Entity Service should be in this domain"
        },
        "entity": {
          "id": "781974596794716162",
          "name": "Financial services"
        }
      },
      {
        "domain": {
          "id": "30",
          "name": "Entities [Entity Service]",
          "description": "Entity Service top level domain, every item that is in Entity Service should be in this domain"
        },
        "entity": {
          "id": "1007360414114435072",
          "name": "Bitcoin cryptocurrency",
          "description": "Bitcoin Cryptocurrency"
        }
      },
      {
        "domain": {
          "id": "65",
          "name": "Interests and Hobbies Vertical",
          "description": "Top level interests and hobbies groupings, like Food or Travel"
        },
        "entity": {
          "id": "781974596148793345",
          "name": "Business & finance"
        }
      },
      {
        "domain": {
          "id": "66",
          "name": "Interests and Hobbies Category",
          "description": "A grouping of interests and hobbies entities, like Novelty Food or Destinations"
        },
        "entity": {
          "id": "847888632711061504",
          "name": "Personal finance",
          "description": "Personal finance"
        }
      },
      {
        "domain": {
          "id": "66",
          "name": "Interests and Hobbies Category",
          "description": "A grouping of interests and hobbies entities, like Novelty Food or Destinations"
        },
        "entity": {
          "id": "913142676819648512",
          "name": "Cryptocurrencies",
          "description": "Cryptocurrency"
        }
      },
      {
        "domain": {
          "id": "131",
          "name": "Unified Twitter Taxonomy",
          "description": "A taxonomy of user interests. "
        },
        "entity": {
          "id": "781974596148793345",
          "name": "Business & finance"
        }
      },
      {
        "domain": {
          "id": "131",
          "name": "Unified Twitter Taxonomy",
          "description": "A taxonomy of user interests. "
        },
        "entity": {
          "id": "913142676819648512",
          "name": "Cryptocurrencies",
          "description": "Cryptocurrency"
        }
      },
      {
        "domain": {
          "id": "131",
          "name": "Unified Twitter Taxonomy",
          "description": "A taxonomy of user interests. "
        },
        "entity": {
          "id": "1007360414114435072",
          "name": "Bitcoin cryptocurrency",
          "description": "Bitcoin Cryptocurrency"
        }
      }
    ],
    "lang": "en",
    "keyword": "bitcoin"
  }
]